[{
    "Data": "31/05/2019",
    "Americanas": 16.21,
    "Poupanca": 16.2
}, {
    "Data": "03/06/2019",
    "Americanas": 16.03,
    "Poupanca": 16.2
}, {
    "Data": "04/06/2019",
    "Americanas": 15.63,
    "Poupanca": 16.2
}, {
    "Data": "05/06/2019",
    "Americanas": 15.73,
    "Poupanca": 16.21
}, {
    "Data": "06/06/2019",
    "Americanas": 15.43,
    "Poupanca": 16.21
}, {
    "Data": "07/06/2019",
    "Americanas": 15.43,
    "Poupanca": 16.21
}, {
    "Data": "10/06/2019",
    "Americanas": 15.68,
    "Poupanca": 16.21
}, {
    "Data": "11/06/2019",
    "Americanas": 16.1,
    "Poupanca": 16.21
}, {
    "Data": "12/06/2019",
    "Americanas": 15.86,
    "Poupanca": 16.22
}, {
    "Data": "13/06/2019",
    "Americanas": 15.73,
    "Poupanca": 16.22
}, {
    "Data": "14/06/2019",
    "Americanas": 15.87,
    "Poupanca": 16.22
}, {
    "Data": "17/06/2019",
    "Americanas": 15.88,
    "Poupanca": 16.22
}, {
    "Data": "18/06/2019",
    "Americanas": 15.79,
    "Poupanca": 16.22
}, {
    "Data": "19/06/2019",
    "Americanas": 15.84,
    "Poupanca": 16.23
}, {
    "Data": "21/06/2019",
    "Americanas": 16.07,
    "Poupanca": 16.23
}, {
    "Data": "24/06/2019",
    "Americanas": 16.4,
    "Poupanca": 16.23
}, {
    "Data": "25/06/2019",
    "Americanas": 16.53,
    "Poupanca": 16.23
}, {
    "Data": "26/06/2019",
    "Americanas": 16.08,
    "Poupanca": 16.23
}, {
    "Data": "27/06/2019",
    "Americanas": 15.95,
    "Poupanca": 16.24
}, {
    "Data": "28/06/2019",
    "Americanas": 16.37,
    "Poupanca": 16.24
}, {
    "Data": "01/07/2019",
    "Americanas": 16.42,
    "Poupanca": 16.24
}, {
    "Data": "02/07/2019",
    "Americanas": 15.89,
    "Poupanca": 16.24
}, {
    "Data": "03/07/2019",
    "Americanas": 15.74,
    "Poupanca": 16.24
}, {
    "Data": "04/07/2019",
    "Americanas": 15.88,
    "Poupanca": 16.25
}, {
    "Data": "05/07/2019",
    "Americanas": 16.23,
    "Poupanca": 16.25
}, {
    "Data": "08/07/2019",
    "Americanas": 16.44,
    "Poupanca": 16.25
}, {
    "Data": "10/07/2019",
    "Americanas": 16.63,
    "Poupanca": 16.25
}, {
    "Data": "11/07/2019",
    "Americanas": 17.2,
    "Poupanca": 16.26
}, {
    "Data": "12/07/2019",
    "Americanas": 17.22,
    "Poupanca": 16.26
}, {
    "Data": "15/07/2019",
    "Americanas": 16.82,
    "Poupanca": 16.26
}, {
    "Data": "16/07/2019",
    "Americanas": 16.65,
    "Poupanca": 16.26
}, {
    "Data": "17/07/2019",
    "Americanas": 16.63,
    "Poupanca": 16.26
}, {
    "Data": "18/07/2019",
    "Americanas": 16.94,
    "Poupanca": 16.27
}, {
    "Data": "19/07/2019",
    "Americanas": 17.33,
    "Poupanca": 16.27
}, {
    "Data": "22/07/2019",
    "Americanas": 16.96,
    "Poupanca": 16.27
}, {
    "Data": "23/07/2019",
    "Americanas": 16.72,
    "Poupanca": 16.27
}, {
    "Data": "24/07/2019",
    "Americanas": 16.71,
    "Poupanca": 16.27
}, {
    "Data": "25/07/2019",
    "Americanas": 16.72,
    "Poupanca": 16.28
}, {
    "Data": "26/07/2019",
    "Americanas": 16.69,
    "Poupanca": 16.28
}, {
    "Data": "29/07/2019",
    "Americanas": 16.9,
    "Poupanca": 16.28
}, {
    "Data": "30/07/2019",
    "Americanas": 17.15,
    "Poupanca": 16.28
}, {
    "Data": "31/07/2019",
    "Americanas": 17.9,
    "Poupanca": 16.28
}, {
    "Data": "01/08/2019",
    "Americanas": 18.11,
    "Poupanca": 16.29
}, {
    "Data": "02/08/2019",
    "Americanas": 18.7,
    "Poupanca": 16.29
}, {
    "Data": "05/08/2019",
    "Americanas": 18.25,
    "Poupanca": 16.29
}, {
    "Data": "06/08/2019",
    "Americanas": 18.1,
    "Poupanca": 16.29
}, {
    "Data": "07/08/2019",
    "Americanas": 17.73,
    "Poupanca": 16.29
}, {
    "Data": "08/08/2019",
    "Americanas": 17.72,
    "Poupanca": 16.3
}, {
    "Data": "09/08/2019",
    "Americanas": 17.96,
    "Poupanca": 16.3
}, {
    "Data": "12/08/2019",
    "Americanas": 18.67,
    "Poupanca": 16.3
}, {
    "Data": "13/08/2019",
    "Americanas": 18.17,
    "Poupanca": 16.3
}, {
    "Data": "14/08/2019",
    "Americanas": 18.35,
    "Poupanca": 16.3
}, {
    "Data": "15/08/2019",
    "Americanas": 17.62,
    "Poupanca": 16.31
}, {
    "Data": "16/08/2019",
    "Americanas": 17.71,
    "Poupanca": 16.31
}, {
    "Data": "19/08/2019",
    "Americanas": 18.01,
    "Poupanca": 16.31
}, {
    "Data": "20/08/2019",
    "Americanas": 17.22,
    "Poupanca": 16.31
}, {
    "Data": "21/08/2019",
    "Americanas": 17.91,
    "Poupanca": 16.31
}, {
    "Data": "22/08/2019",
    "Americanas": 17.61,
    "Poupanca": 16.32
}, {
    "Data": "23/08/2019",
    "Americanas": 16.89,
    "Poupanca": 16.32
}, {
    "Data": "26/08/2019",
    "Americanas": 16.64,
    "Poupanca": 16.32
}, {
    "Data": "27/08/2019",
    "Americanas": 16.62,
    "Poupanca": 16.32
}, {
    "Data": "28/08/2019",
    "Americanas": 16.71,
    "Poupanca": 16.32
}, {
    "Data": "29/08/2019",
    "Americanas": 17.15,
    "Poupanca": 16.33
}, {
    "Data": "30/08/2019",
    "Americanas": 18.21,
    "Poupanca": 16.33
}, {
    "Data": "02/09/2019",
    "Americanas": 18.53,
    "Poupanca": 16.33
}, {
    "Data": "03/09/2019",
    "Americanas": 18.46,
    "Poupanca": 16.33
}, {
    "Data": "04/09/2019",
    "Americanas": 18.75,
    "Poupanca": 16.34
}, {
    "Data": "05/09/2019",
    "Americanas": 18.9,
    "Poupanca": 16.34
}, {
    "Data": "06/09/2019",
    "Americanas": 18.77,
    "Poupanca": 16.34
}, {
    "Data": "09/09/2019",
    "Americanas": 18.61,
    "Poupanca": 16.34
}, {
    "Data": "10/09/2019",
    "Americanas": 17.65,
    "Poupanca": 16.34
}, {
    "Data": "11/09/2019",
    "Americanas": 17.97,
    "Poupanca": 16.35
}, {
    "Data": "12/09/2019",
    "Americanas": 18.73,
    "Poupanca": 16.35
}, {
    "Data": "13/09/2019",
    "Americanas": 18.57,
    "Poupanca": 16.35
}, {
    "Data": "16/09/2019",
    "Americanas": 18.24,
    "Poupanca": 16.35
}, {
    "Data": "17/09/2019",
    "Americanas": 18.25,
    "Poupanca": 16.35
}, {
    "Data": "18/09/2019",
    "Americanas": 18.88,
    "Poupanca": 16.36
}, {
    "Data": "19/09/2019",
    "Americanas": 19.2,
    "Poupanca": 16.36
}, {
    "Data": "20/09/2019",
    "Americanas": 19.56,
    "Poupanca": 16.36
}, {
    "Data": "23/09/2019",
    "Americanas": 19.39,
    "Poupanca": 16.36
}, {
    "Data": "24/09/2019",
    "Americanas": 19.49,
    "Poupanca": 16.36
}, {
    "Data": "25/09/2019",
    "Americanas": 19.6,
    "Poupanca": 16.37
}, {
    "Data": "26/09/2019",
    "Americanas": 19.75,
    "Poupanca": 16.37
}, {
    "Data": "27/09/2019",
    "Americanas": 19.81,
    "Poupanca": 16.37
}, {
    "Data": "30/09/2019",
    "Americanas": 19.68,
    "Poupanca": 16.37
}, {
    "Data": "01/10/2019",
    "Americanas": 19.77,
    "Poupanca": 16.37
}, {
    "Data": "02/10/2019",
    "Americanas": 19.42,
    "Poupanca": 16.38
}, {
    "Data": "03/10/2019",
    "Americanas": 19.1,
    "Poupanca": 16.38
}, {
    "Data": "04/10/2019",
    "Americanas": 19.03,
    "Poupanca": 16.38
}, {
    "Data": "07/10/2019",
    "Americanas": 19.36,
    "Poupanca": 16.38
}, {
    "Data": "08/10/2019",
    "Americanas": 19.41,
    "Poupanca": 16.38
}, {
    "Data": "09/10/2019",
    "Americanas": 19.19,
    "Poupanca": 16.39
}, {
    "Data": "10/10/2019",
    "Americanas": 19.58,
    "Poupanca": 16.39
}, {
    "Data": "11/10/2019",
    "Americanas": 19.65,
    "Poupanca": 16.39
}, {
    "Data": "14/10/2019",
    "Americanas": 20.28,
    "Poupanca": 16.39
}, {
    "Data": "15/10/2019",
    "Americanas": 20.77,
    "Poupanca": 16.4
}, {
    "Data": "16/10/2019",
    "Americanas": 20.88,
    "Poupanca": 16.4
}, {
    "Data": "17/10/2019",
    "Americanas": 21.08,
    "Poupanca": 16.4
}, {
    "Data": "18/10/2019",
    "Americanas": 21.03,
    "Poupanca": 16.4
}, {
    "Data": "21/10/2019",
    "Americanas": 20.82,
    "Poupanca": 16.4
}, {
    "Data": "22/10/2019",
    "Americanas": 20.87,
    "Poupanca": 16.41
}, {
    "Data": "23/10/2019",
    "Americanas": 20.59,
    "Poupanca": 16.41
}, {
    "Data": "24/10/2019",
    "Americanas": 20.72,
    "Poupanca": 16.41
}, {
    "Data": "25/10/2019",
    "Americanas": 20.58,
    "Poupanca": 16.41
}, {
    "Data": "28/10/2019",
    "Americanas": 20.15,
    "Poupanca": 16.41
}, {
    "Data": "29/10/2019",
    "Americanas": 20.22,
    "Poupanca": 16.42
}, {
    "Data": "30/10/2019",
    "Americanas": 20.19,
    "Poupanca": 16.42
}, {
    "Data": "31/10/2019",
    "Americanas": 20.83,
    "Poupanca": 16.42
}, {
    "Data": "01/11/2019",
    "Americanas": 19.71,
    "Poupanca": 16.42
}, {
    "Data": "04/11/2019",
    "Americanas": 20.13,
    "Poupanca": 16.42
}, {
    "Data": "05/11/2019",
    "Americanas": 19.94,
    "Poupanca": 16.43
}, {
    "Data": "06/11/2019",
    "Americanas": 19.81,
    "Poupanca": 16.43
}, {
    "Data": "07/11/2019",
    "Americanas": 20.3,
    "Poupanca": 16.43
}, {
    "Data": "08/11/2019",
    "Americanas": 19.97,
    "Poupanca": 16.43
}, {
    "Data": "11/11/2019",
    "Americanas": 19.1,
    "Poupanca": 16.43
}, {
    "Data": "12/11/2019",
    "Americanas": 19.57,
    "Poupanca": 16.44
}, {
    "Data": "13/11/2019",
    "Americanas": 19.25,
    "Poupanca": 16.44
}, {
    "Data": "14/11/2019",
    "Americanas": 19.34,
    "Poupanca": 16.44
}, {
    "Data": "18/11/2019",
    "Americanas": 20.04,
    "Poupanca": 16.44
}, {
    "Data": "19/11/2019",
    "Americanas": 19.59,
    "Poupanca": 16.44
}, {
    "Data": "21/11/2019",
    "Americanas": 19.75,
    "Poupanca": 16.45
}, {
    "Data": "22/11/2019",
    "Americanas": 20.1,
    "Poupanca": 16.45
}, {
    "Data": "25/11/2019",
    "Americanas": 20.12,
    "Poupanca": 16.45
}, {
    "Data": "26/11/2019",
    "Americanas": 20.1,
    "Poupanca": 16.45
}, {
    "Data": "27/11/2019",
    "Americanas": 20.25,
    "Poupanca": 16.46
}, {
    "Data": "28/11/2019",
    "Americanas": 21.08,
    "Poupanca": 16.46
}, {
    "Data": "29/11/2019",
    "Americanas": 21.73,
    "Poupanca": 16.46
}, {
    "Data": "02/12/2019",
    "Americanas": 22.03,
    "Poupanca": 16.46
}, {
    "Data": "03/12/2019",
    "Americanas": 22.59,
    "Poupanca": 16.46
}, {
    "Data": "04/12/2019",
    "Americanas": 22.73,
    "Poupanca": 16.47
}, {
    "Data": "05/12/2019",
    "Americanas": 22.87,
    "Poupanca": 16.47
}, {
    "Data": "06/12/2019",
    "Americanas": 22.76,
    "Poupanca": 16.47
}, {
    "Data": "09/12/2019",
    "Americanas": 24.26,
    "Poupanca": 16.47
}, {
    "Data": "10/12/2019",
    "Americanas": 24.84,
    "Poupanca": 16.47
}, {
    "Data": "11/12/2019",
    "Americanas": 24.77,
    "Poupanca": 16.48
}, {
    "Data": "12/12/2019",
    "Americanas": 24.87,
    "Poupanca": 16.48
}, {
    "Data": "13/12/2019",
    "Americanas": 26.41,
    "Poupanca": 16.48
}, {
    "Data": "16/12/2019",
    "Americanas": 26.98,
    "Poupanca": 16.48
}, {
    "Data": "17/12/2019",
    "Americanas": 26.51,
    "Poupanca": 16.48
}, {
    "Data": "18/12/2019",
    "Americanas": 25.8,
    "Poupanca": 16.49
}, {
    "Data": "19/12/2019",
    "Americanas": 25.58,
    "Poupanca": 16.49
}, {
    "Data": "20/12/2019",
    "Americanas": 25.96,
    "Poupanca": 16.49
}, {
    "Data": "23/12/2019",
    "Americanas": 26.44,
    "Poupanca": 16.49
}, {
    "Data": "26/12/2019",
    "Americanas": 26.63,
    "Poupanca": 16.49
}, {
    "Data": "27/12/2019",
    "Americanas": 26.79,
    "Poupanca": 16.5
}, {
    "Data": "30/12/2019",
    "Americanas": 26.17,
    "Poupanca": 16.5
}, {
    "Data": "02/01/2020",
    "Americanas": 25.99,
    "Poupanca": 16.5
}, {
    "Data": "03/01/2020",
    "Americanas": 26.45,
    "Poupanca": 16.5
}, {
    "Data": "06/01/2020",
    "Americanas": 26.76,
    "Poupanca": 16.5
}, {
    "Data": "07/01/2020",
    "Americanas": 26.52,
    "Poupanca": 16.51
}, {
    "Data": "08/01/2020",
    "Americanas": 26.02,
    "Poupanca": 16.51
}, {
    "Data": "09/01/2020",
    "Americanas": 25.85,
    "Poupanca": 16.51
}, {
    "Data": "10/01/2020",
    "Americanas": 26.64,
    "Poupanca": 16.51
}, {
    "Data": "13/01/2020",
    "Americanas": 26.56,
    "Poupanca": 16.52
}, {
    "Data": "14/01/2020",
    "Americanas": 27.11,
    "Poupanca": 16.52
}, {
    "Data": "15/01/2020",
    "Americanas": 27.68,
    "Poupanca": 16.52
}, {
    "Data": "16/01/2020",
    "Americanas": 27.9,
    "Poupanca": 16.52
}, {
    "Data": "17/01/2020",
    "Americanas": 28.0,
    "Poupanca": 16.52
}, {
    "Data": "20/01/2020",
    "Americanas": 28.16,
    "Poupanca": 16.53
}, {
    "Data": "21/01/2020",
    "Americanas": 28.86,
    "Poupanca": 16.53
}, {
    "Data": "22/01/2020",
    "Americanas": 29.32,
    "Poupanca": 16.53
}, {
    "Data": "23/01/2020",
    "Americanas": 28.37,
    "Poupanca": 16.53
}, {
    "Data": "24/01/2020",
    "Americanas": 29.06,
    "Poupanca": 16.53
}, {
    "Data": "27/01/2020",
    "Americanas": 28.26,
    "Poupanca": 16.54
}, {
    "Data": "28/01/2020",
    "Americanas": 28.65,
    "Poupanca": 16.54
}, {
    "Data": "29/01/2020",
    "Americanas": 28.6,
    "Poupanca": 16.54
}, {
    "Data": "30/01/2020",
    "Americanas": 28.0,
    "Poupanca": 16.54
}, {
    "Data": "31/01/2020",
    "Americanas": 27.15,
    "Poupanca": 16.54
}, {
    "Data": "03/02/2020",
    "Americanas": 27.55,
    "Poupanca": 16.55
}, {
    "Data": "04/02/2020",
    "Americanas": 27.61,
    "Poupanca": 16.55
}, {
    "Data": "05/02/2020",
    "Americanas": 28.0,
    "Poupanca": 16.55
}, {
    "Data": "06/02/2020",
    "Americanas": 27.8,
    "Poupanca": 16.55
}, {
    "Data": "07/02/2020",
    "Americanas": 26.5,
    "Poupanca": 16.55
}, {
    "Data": "10/02/2020",
    "Americanas": 26.05,
    "Poupanca": 16.56
}, {
    "Data": "11/02/2020",
    "Americanas": 26.25,
    "Poupanca": 16.56
}, {
    "Data": "12/02/2020",
    "Americanas": 27.11,
    "Poupanca": 16.56
}, {
    "Data": "13/02/2020",
    "Americanas": 26.91,
    "Poupanca": 16.56
}, {
    "Data": "14/02/2020",
    "Americanas": 27.31,
    "Poupanca": 16.57
}, {
    "Data": "17/02/2020",
    "Americanas": 27.25,
    "Poupanca": 16.57
}, {
    "Data": "18/02/2020",
    "Americanas": 27.32,
    "Poupanca": 16.57
}, {
    "Data": "19/02/2020",
    "Americanas": 27.02,
    "Poupanca": 16.57
}, {
    "Data": "20/02/2020",
    "Americanas": 27.1,
    "Poupanca": 16.57
}, {
    "Data": "21/02/2020",
    "Americanas": 27.0,
    "Poupanca": 16.58
}, {
    "Data": "26/02/2020",
    "Americanas": 27.09,
    "Poupanca": 16.58
}, {
    "Data": "27/02/2020",
    "Americanas": 26.04,
    "Poupanca": 16.58
}, {
    "Data": "28/02/2020",
    "Americanas": 26.03,
    "Poupanca": 16.58
}, {
    "Data": "02/03/2020",
    "Americanas": 26.5,
    "Poupanca": 16.58
}, {
    "Data": "03/03/2020",
    "Americanas": 26.8,
    "Poupanca": 16.59
}, {
    "Data": "04/03/2020",
    "Americanas": 28.01,
    "Poupanca": 16.59
}, {
    "Data": "05/03/2020",
    "Americanas": 27.13,
    "Poupanca": 16.59
}, {
    "Data": "06/03/2020",
    "Americanas": 24.89,
    "Poupanca": 16.59
}, {
    "Data": "09/03/2020",
    "Americanas": 21.1,
    "Poupanca": 16.59
}, {
    "Data": "10/03/2020",
    "Americanas": 22.75,
    "Poupanca": 16.6
}, {
    "Data": "11/03/2020",
    "Americanas": 22.31,
    "Poupanca": 16.6
}, {
    "Data": "12/03/2020",
    "Americanas": 18.0,
    "Poupanca": 16.6
}, {
    "Data": "13/03/2020",
    "Americanas": 19.5,
    "Poupanca": 16.6
}, {
    "Data": "16/03/2020",
    "Americanas": 17.99,
    "Poupanca": 16.61
}, {
    "Data": "17/03/2020",
    "Americanas": 18.19,
    "Poupanca": 16.61
}, {
    "Data": "18/03/2020",
    "Americanas": 16.59,
    "Poupanca": 16.61
}, {
    "Data": "19/03/2020",
    "Americanas": 15.83,
    "Poupanca": 16.61
}, {
    "Data": "20/03/2020",
    "Americanas": 17.21,
    "Poupanca": 16.61
}, {
    "Data": "23/03/2020",
    "Americanas": 17.43,
    "Poupanca": 16.62
}, {
    "Data": "24/03/2020",
    "Americanas": 18.89,
    "Poupanca": 16.62
}, {
    "Data": "25/03/2020",
    "Americanas": 19.16,
    "Poupanca": 16.62
}, {
    "Data": "26/03/2020",
    "Americanas": 20.45,
    "Poupanca": 16.62
}, {
    "Data": "27/03/2020",
    "Americanas": 19.9,
    "Poupanca": 16.62
}, {
    "Data": "30/03/2020",
    "Americanas": 19.06,
    "Poupanca": 16.63
}, {
    "Data": "31/03/2020",
    "Americanas": 19.01,
    "Poupanca": 16.63
}, {
    "Data": "01/04/2020",
    "Americanas": 17.54,
    "Poupanca": 16.63
}, {
    "Data": "02/04/2020",
    "Americanas": 18.1,
    "Poupanca": 16.63
}, {
    "Data": "03/04/2020",
    "Americanas": 18.5,
    "Poupanca": 16.63
}, {
    "Data": "06/04/2020",
    "Americanas": 18.5,
    "Poupanca": 16.64
}, {
    "Data": "07/04/2020",
    "Americanas": 20.57,
    "Poupanca": 16.64
}, {
    "Data": "08/04/2020",
    "Americanas": 20.49,
    "Poupanca": 16.64
}, {
    "Data": "09/04/2020",
    "Americanas": 22.0,
    "Poupanca": 16.64
}, {
    "Data": "13/04/2020",
    "Americanas": 21.13,
    "Poupanca": 16.64
}, {
    "Data": "14/04/2020",
    "Americanas": 21.14,
    "Poupanca": 16.65
}, {
    "Data": "15/04/2020",
    "Americanas": 20.31,
    "Poupanca": 16.65
}, {
    "Data": "16/04/2020",
    "Americanas": 21.94,
    "Poupanca": 16.65
}, {
    "Data": "17/04/2020",
    "Americanas": 22.92,
    "Poupanca": 16.65
}, {
    "Data": "20/04/2020",
    "Americanas": 21.4,
    "Poupanca": 16.66
}, {
    "Data": "22/04/2020",
    "Americanas": 23.01,
    "Poupanca": 16.66
}, {
    "Data": "23/04/2020",
    "Americanas": 25.65,
    "Poupanca": 16.66
}, {
    "Data": "24/04/2020",
    "Americanas": 23.68,
    "Poupanca": 16.66
}, {
    "Data": "27/04/2020",
    "Americanas": 23.63,
    "Poupanca": 16.66
}, {
    "Data": "28/04/2020",
    "Americanas": 24.38,
    "Poupanca": 16.67
}, {
    "Data": "29/04/2020",
    "Americanas": 25.82,
    "Poupanca": 16.67
}, {
    "Data": "30/04/2020",
    "Americanas": 25.34,
    "Poupanca": 16.67
}, {
    "Data": "04/05/2020",
    "Americanas": 24.0,
    "Poupanca": 16.67
}, {
    "Data": "05/05/2020",
    "Americanas": 25.42,
    "Poupanca": 16.67
}, {
    "Data": "06/05/2020",
    "Americanas": 25.97,
    "Poupanca": 16.68
}, {
    "Data": "07/05/2020",
    "Americanas": 28.0,
    "Poupanca": 16.68
}, {
    "Data": "08/05/2020",
    "Americanas": 27.69,
    "Poupanca": 16.68
}, {
    "Data": "11/05/2020",
    "Americanas": 26.51,
    "Poupanca": 16.68
}, {
    "Data": "12/05/2020",
    "Americanas": 26.3,
    "Poupanca": 16.68
}, {
    "Data": "13/05/2020",
    "Americanas": 26.7,
    "Poupanca": 16.69
}, {
    "Data": "14/05/2020",
    "Americanas": 26.9,
    "Poupanca": 16.69
}, {
    "Data": "15/05/2020",
    "Americanas": 27.0,
    "Poupanca": 16.69
}, {
    "Data": "18/05/2020",
    "Americanas": 27.48,
    "Poupanca": 16.69
}, {
    "Data": "19/05/2020",
    "Americanas": 26.95,
    "Poupanca": 16.7
}, {
    "Data": "20/05/2020",
    "Americanas": 27.82,
    "Poupanca": 16.7
}, {
    "Data": "21/05/2020",
    "Americanas": 26.84,
    "Poupanca": 16.7
}, {
    "Data": "22/05/2020",
    "Americanas": 26.54,
    "Poupanca": 16.7
}, {
    "Data": "25/05/2020",
    "Americanas": 26.3,
    "Poupanca": 16.7
}, {
    "Data": "26/05/2020",
    "Americanas": 26.2,
    "Poupanca": 16.71
}, {
    "Data": "27/05/2020",
    "Americanas": 27.3,
    "Poupanca": 16.71
}, {
    "Data": "28/05/2020",
    "Americanas": 28.59,
    "Poupanca": 16.71
}, {
    "Data": "29/05/2020",
    "Americanas": 28.68,
    "Poupanca": 16.71
}]